blc/__init__.py
blc/barbell.py
blc/blc.py
blc/plates.py
blc_py-0.1.2.dist-info/METADATA
blc_py-0.1.2.dist-info/WHEEL
blc_py-0.1.2.dist-info/top_level.txt
blc_py-0.1.2.dist-info/RECORD
