Metadata-Version: 2.4
Name: blc-py
Version: 0.1.2
Summary: Barbell Loading Calculator for Olympic Weightlifting
Requires-Python: >=3.12
Requires-Dist: build>=1.2.2.post1
Requires-Dist: pytest>=8.4.1
